.bumpversion.cfg
.gitignore
.pre-commit-config.yaml
.readthedocs.yml
.restyled.yaml
.semantic.yml
CITATION.cff
CONTRIBUTING.md
LICENSE
MANIFEST.in
README.md
pyproject.toml
setup.cfg
setup.py
.github/workflows/cd.yml
.github/workflows/ci.yml
.github/workflows/head-dependencies.yml
.tools/git-cleanup.sh
binder/postBuild
docs/make.bat
docs/requirements.txt
docs/source/api.rst
docs/source/conf.py
docs/source/guide.rst
docs/source/index.rst
docs/source/install.rst
docs/source/_static/mplhep.png
examples/Examples.ipynb
img/Example1.png
img/Example2.png
img/FontComp.png
img/style0.png
img/style1.png
img/style2.png
src/embedded_mplhep.egg-info/PKG-INFO
src/embedded_mplhep.egg-info/SOURCES.txt
src/embedded_mplhep.egg-info/dependency_links.txt
src/embedded_mplhep.egg-info/not-zip-safe
src/embedded_mplhep.egg-info/requires.txt
src/embedded_mplhep.egg-info/top_level.txt
src/mplhep/__init__.py
src/mplhep/_deprecate.py
src/mplhep/_tools.py
src/mplhep/_version.py
src/mplhep/_version.pyi
src/mplhep/alice.py
src/mplhep/atlas.py
src/mplhep/cms.py
src/mplhep/error_estimation.py
src/mplhep/label.py
src/mplhep/lhcb.py
src/mplhep/plot.py
src/mplhep/utils.py
src/mplhep/styles/__init__.py
src/mplhep/styles/alice.py
src/mplhep/styles/atlas.py
src/mplhep/styles/cms.py
src/mplhep/styles/lhcb.py
tests/test_basic.py
tests/test_inputs.py
tests/test_mock.py
tests/test_notebooks.py
tests/test_styles.py
tests/baseline/test_hist2dplot.png
tests/baseline/test_hist2dplot_cbar_False.png
tests/baseline/test_hist2dplot_cbar_True.png
tests/baseline/test_hist2dplot_cbar_subplots.png
tests/baseline/test_hist2dplot_custom_labels.png
tests/baseline/test_hist2dplot_flow.png
tests/baseline/test_hist2dplot_inputs_nobin.png
tests/baseline/test_histplot.png
tests/baseline/test_histplot_density.png
tests/baseline/test_histplot_flow.png
tests/baseline/test_histplot_hist_flow.png
tests/baseline/test_histplot_kwargs.png
tests/baseline/test_histplot_multiple.png
tests/baseline/test_histplot_real.png
tests/baseline/test_histplot_stack.png
tests/baseline/test_histplot_type_flow.png
tests/baseline/test_histplot_types.png
tests/baseline/test_histplot_uproot_flow.png
tests/baseline/test_histplot_w2.png
tests/baseline/test_histplot_w2_noscipy.png
