Metadata-Version: 2.1
Name: embedded-mplhep
Version: 0.5.13
Summary: Matplotlib styles for HEP
Home-page: https://github.com/scikit-hep/mplhep
Author: andrzejnovak
Author-email: "novak5andrzej@gmail.com"
Maintainer: Scikit-HEP
Maintainer-email: scikit-hep-admins@googlegroups.com
License: MIT
Classifier: Framework :: Matplotlib
Classifier: Intended Audience :: Science/Research
Classifier: License :: OSI Approved :: MIT License
Classifier: Programming Language :: Python :: 3
Classifier: Programming Language :: Python :: 3 :: Only
Classifier: Programming Language :: Python :: 3.8
Classifier: Programming Language :: Python :: 3.9
Classifier: Programming Language :: Python :: 3.10
Classifier: Programming Language :: Python :: 3.11
Classifier: Topic :: Scientific/Engineering :: Physics
Requires-Python: >=3.8
Provides-Extra: test
Provides-Extra: dev
Provides-Extra: all
License-File: LICENSE
